rsaitehu/scmamp_python.py
rsaitehu/stats.py
rsaitehu_stats-0.0.2.dist-info/METADATA
rsaitehu_stats-0.0.2.dist-info/WHEEL
rsaitehu_stats-0.0.2.dist-info/top_level.txt
rsaitehu_stats-0.0.2.dist-info/RECORD
